setup.py
big_letters/__init__.py
big_letters/printer.py
big_letters.egg-info/PKG-INFO
big_letters.egg-info/SOURCES.txt
big_letters.egg-info/dependency_links.txt
big_letters.egg-info/top_level.txt