Metadata-Version: 1.0
Name: big-letters
Version: 0.0.3
Summary: prints text in big letters in your terminal
Home-page: UNKNOWN
Author: Uwe Schmitt
Author-email: UNKNOWN
License: BSD
Platform: UNKNOWN
